{
    "success": true,
    "data": {
        "referense": [
            {
                "id": 13,
                "username": "test 13",
                "game_id": "492271",
                "score": 0,
                "created_at": "2021-03-04 06:42:50"
            },
            {
                "id": 14,
                "username": "test 14",
                "game_id": "927135",
                "score": 0,
                "created_at": "2021-03-04 06:47:32"
            }
        ]
    },
    "message": "Reference successfully."
}